rdflib_shim/__init__.py
rdflib_shim-1.0.1.dist-info/AUTHORS
rdflib_shim-1.0.1.dist-info/LICENSE
rdflib_shim-1.0.1.dist-info/METADATA
rdflib_shim-1.0.1.dist-info/WHEEL
rdflib_shim-1.0.1.dist-info/top_level.txt
rdflib_shim-1.0.1.dist-info/RECORD
